.gitignore
CHANGES.rst
LICENSE.txt
Makefile
README.rst
development.ini
production.ini
setup.cfg
setup.py
Poulda.egg-info/PKG-INFO
Poulda.egg-info/SOURCES.txt
Poulda.egg-info/dependency_links.txt
Poulda.egg-info/entry_points.txt
Poulda.egg-info/not-zip-safe
Poulda.egg-info/requires.txt
Poulda.egg-info/top_level.txt
docs/bg.png
docs/home-thumbnail.png
docs/home.png
docs/index.html
docs/main.css
docs/upload-thumbnail.png
docs/upload.png
poulda/__init__.py
poulda/app.py
poulda/auth.py
poulda/i18n.py
poulda/models.py
poulda/utils.py
poulda/views.py
poulda/locale/poulda.pot
poulda/locale/fr/LC_MESSAGES/poulda.mo
poulda/locale/fr/LC_MESSAGES/poulda.po
poulda/static/main.css
poulda/static/progress_bar.png
poulda/static/upload.js
poulda/templates/home.pt
poulda/templates/layout.pt
poulda/templates/success.pt
poulda/templates/upload.pt
poulda/tests/__init__.py
poulda/tests/test_auth.py
poulda/tests/test_i18n.py
poulda/tests/test_utils.py
poulda/tests/data/body_small.txt
poulda/tests/js/tests.html
poulda/tests/js/tests.js
poulda/tests/js/qunit/qunit.css
poulda/tests/js/qunit/qunit.js