Metadata-Version: 1.0
Name: Poulda
Version: 0.9
Summary: Poulda - a simple upload service
Home-page: http://packages.python.org/Poulda
Author: Damien Baty
Author-email: damien.baty.remove@gmail.com
License: UNKNOWN
Keywords: web wsgi pyramid file upload
Platform: UNKNOWN
Classifier: Development Status :: 4 - Beta
Classifier: Framework :: Pylons
Classifier: License :: OSI Approved :: BSD License
Classifier: Natural Language :: English
Classifier: Natural Language :: French
Classifier: Programming Language :: Python :: 2.7
